[
  {
    "ContainingType": "Institute.Controllers.AdminController",
    "Method": "GetStudents",
    "RelativePath": "api/Admin/Students",
    "HttpMethod": "GET",
    "IsController": true,
    "Order": 0,
    "Parameters": [],
    "ReturnTypes": []
  },
  {
    "ContainingType": "Institute.Controllers.AdminController",
    "Method": "CreateStudent",
    "RelativePath": "api/Admin/Students",
    "HttpMethod": "POST",
    "IsController": true,
    "Order": 0,
    "Parameters": [
      {
        "Name": "student",
        "Type": "Institute.Models.Student",
        "IsRequired": true
      }
    ],
    "ReturnTypes": []
  },
  {
    "ContainingType": "Institute.Controllers.AdminController",
    "Method": "GetStudent",
    "RelativePath": "api/Admin/Students/{id}",
    "HttpMethod": "GET",
    "IsController": true,
    "Order": 0,
    "Parameters": [
      {
        "Name": "id",
        "Type": "System.Int32",
        "IsRequired": true
      }
    ],
    "ReturnTypes": []
  },
  {
    "ContainingType": "Institute.Controllers.AdminController",
    "Method": "UpdateStudent",
    "RelativePath": "api/Admin/Students/{id}",
    "HttpMethod": "PUT",
    "IsController": true,
    "Order": 0,
    "Parameters": [
      {
        "Name": "id",
        "Type": "System.Int32",
        "IsRequired": true
      },
      {
        "Name": "student",
        "Type": "Institute.Models.Student",
        "IsRequired": true
      }
    ],
    "ReturnTypes": []
  },
  {
    "ContainingType": "Institute.Controllers.AdminController",
    "Method": "DeleteStudent",
    "RelativePath": "api/Admin/Students/{id}",
    "HttpMethod": "DELETE",
    "IsController": true,
    "Order": 0,
    "Parameters": [
      {
        "Name": "id",
        "Type": "System.Int32",
        "IsRequired": true
      }
    ],
    "ReturnTypes": []
  },
  {
    "ContainingType": "Institute.Controllers.AdminController",
    "Method": "GetTrainees",
    "RelativePath": "api/Admin/Trainees",
    "HttpMethod": "GET",
    "IsController": true,
    "Order": 0,
    "Parameters": [],
    "ReturnTypes": []
  },
  {
    "ContainingType": "Institute.Controllers.AdminController",
    "Method": "CreateTrainee",
    "RelativePath": "api/Admin/Trainees",
    "HttpMethod": "POST",
    "IsController": true,
    "Order": 0,
    "Parameters": [
      {
        "Name": "trainee",
        "Type": "Institute.Models.Trainee",
        "IsRequired": true
      }
    ],
    "ReturnTypes": []
  },
  {
    "ContainingType": "Institute.Controllers.AdminController",
    "Method": "GetTrainee",
    "RelativePath": "api/Admin/Trainees/{id}",
    "HttpMethod": "GET",
    "IsController": true,
    "Order": 0,
    "Parameters": [
      {
        "Name": "id",
        "Type": "System.Int32",
        "IsRequired": true
      }
    ],
    "ReturnTypes": []
  },
  {
    "ContainingType": "Institute.Controllers.AdminController",
    "Method": "UpdateTrainee",
    "RelativePath": "api/Admin/Trainees/{id}",
    "HttpMethod": "PUT",
    "IsController": true,
    "Order": 0,
    "Parameters": [
      {
        "Name": "id",
        "Type": "System.Int32",
        "IsRequired": true
      },
      {
        "Name": "trainee",
        "Type": "Institute.Models.Trainee",
        "IsRequired": true
      }
    ],
    "ReturnTypes": []
  },
  {
    "ContainingType": "Institute.Controllers.AdminController",
    "Method": "DeleteTrainee",
    "RelativePath": "api/Admin/Trainees/{id}",
    "HttpMethod": "DELETE",
    "IsController": true,
    "Order": 0,
    "Parameters": [
      {
        "Name": "id",
        "Type": "System.Int32",
        "IsRequired": true
      }
    ],
    "ReturnTypes": []
  },
  {
    "ContainingType": "Institute.Controllers.AdminController",
    "Method": "GetUsers",
    "RelativePath": "api/Admin/Users",
    "HttpMethod": "GET",
    "IsController": true,
    "Order": 0,
    "Parameters": [],
    "ReturnTypes": []
  },
  {
    "ContainingType": "Institute.Controllers.AdminController",
    "Method": "CreateUser",
    "RelativePath": "api/Admin/Users",
    "HttpMethod": "POST",
    "IsController": true,
    "Order": 0,
    "Parameters": [
      {
        "Name": "user",
        "Type": "Institute.Models.User",
        "IsRequired": true
      }
    ],
    "ReturnTypes": []
  },
  {
    "ContainingType": "Institute.Controllers.AdminController",
    "Method": "GetUser",
    "RelativePath": "api/Admin/Users/{id}",
    "HttpMethod": "GET",
    "IsController": true,
    "Order": 0,
    "Parameters": [
      {
        "Name": "id",
        "Type": "System.Int32",
        "IsRequired": true
      }
    ],
    "ReturnTypes": []
  },
  {
    "ContainingType": "Institute.Controllers.AdminController",
    "Method": "UpdateUser",
    "RelativePath": "api/Admin/Users/{id}",
    "HttpMethod": "PUT",
    "IsController": true,
    "Order": 0,
    "Parameters": [
      {
        "Name": "id",
        "Type": "System.Int32",
        "IsRequired": true
      },
      {
        "Name": "user",
        "Type": "Institute.Models.User",
        "IsRequired": true
      }
    ],
    "ReturnTypes": []
  },
  {
    "ContainingType": "Institute.Controllers.AdminController",
    "Method": "DeleteUser",
    "RelativePath": "api/Admin/Users/{id}",
    "HttpMethod": "DELETE",
    "IsController": true,
    "Order": 0,
    "Parameters": [
      {
        "Name": "id",
        "Type": "System.Int32",
        "IsRequired": true
      }
    ],
    "ReturnTypes": []
  },
  {
    "ContainingType": "Institute.Controllers.AuthenticationController",
    "Method": "SignIn",
    "RelativePath": "api/Authentication/signin",
    "HttpMethod": "POST",
    "IsController": true,
    "Order": 0,
    "Parameters": [
      {
        "Name": "model",
        "Type": "Institute.Models.User",
        "IsRequired": true
      }
    ],
    "ReturnTypes": []
  },
  {
    "ContainingType": "Institute.Controllers.StudentController",
    "Method": "GetStudentDetails",
    "RelativePath": "api/Student/Details/{id}",
    "HttpMethod": "GET",
    "IsController": true,
    "Order": 0,
    "Parameters": [
      {
        "Name": "id",
        "Type": "System.Int32",
        "IsRequired": true
      }
    ],
    "ReturnTypes": []
  },
  {
    "ContainingType": "Institute.Controllers.StudentController",
    "Method": "RegisterStudent",
    "RelativePath": "api/Student/Register",
    "HttpMethod": "POST",
    "IsController": true,
    "Order": 0,
    "Parameters": [
      {
        "Name": "student",
        "Type": "Institute.Models.Student",
        "IsRequired": true
      }
    ],
    "ReturnTypes": []
  },
  {
    "ContainingType": "Institute.Controllers.StudentController",
    "Method": "UpdateStudent",
    "RelativePath": "api/Student/Update/{id}",
    "HttpMethod": "PUT",
    "IsController": true,
    "Order": 0,
    "Parameters": [
      {
        "Name": "id",
        "Type": "System.Int32",
        "IsRequired": true
      },
      {
        "Name": "student",
        "Type": "Institute.Models.Student",
        "IsRequired": true
      }
    ],
    "ReturnTypes": []
  },
  {
    "ContainingType": "Institute.Controllers.TraineeController",
    "Method": "GetTraineeDetails",
    "RelativePath": "api/Trainee/Details/{id}",
    "HttpMethod": "GET",
    "IsController": true,
    "Order": 0,
    "Parameters": [
      {
        "Name": "id",
        "Type": "System.Int32",
        "IsRequired": true
      }
    ],
    "ReturnTypes": []
  },
  {
    "ContainingType": "Institute.Controllers.TraineeController",
    "Method": "UpdateTrainee",
    "RelativePath": "api/Trainee/Update/{id}",
    "HttpMethod": "PUT",
    "IsController": true,
    "Order": 0,
    "Parameters": [
      {
        "Name": "id",
        "Type": "System.Int32",
        "IsRequired": true
      },
      {
        "Name": "updatedTrainee",
        "Type": "Institute.Models.Trainee",
        "IsRequired": true
      }
    ],
    "ReturnTypes": []
  },
  {
    "ContainingType": "Institute.Controllers.WeatherForecastController",
    "Method": "Get",
    "RelativePath": "WeatherForecast",
    "HttpMethod": "GET",
    "IsController": true,
    "Order": 0,
    "Parameters": [],
    "ReturnTypes": [
      {
        "Type": "System.Collections.Generic.IEnumerable\u00601[[Institute.WeatherForecast, Institute, Version=1.0.0.0, Culture=neutral, PublicKeyToken=null]]",
        "MediaTypes": [
          "text/plain",
          "application/json",
          "text/json"
        ],
        "StatusCode": 200
      }
    ],
    "EndpointName": "GetWeatherForecast"
  }
]